airflow_gcpsecretmanager_adapter/__init__.py
airflow_gcpsecretmanager_adapter/secret_manager_backend_adapter.py
airflow_gcpsecretmanager_adapter-2.0.1.dist-info/LICENSE
airflow_gcpsecretmanager_adapter-2.0.1.dist-info/METADATA
airflow_gcpsecretmanager_adapter-2.0.1.dist-info/WHEEL
airflow_gcpsecretmanager_adapter-2.0.1.dist-info/top_level.txt
airflow_gcpsecretmanager_adapter-2.0.1.dist-info/RECORD
