Metadata-Version: 2.1
Name: airflow-gcpsecretmanager-adapter
Version: 2.0.1
Summary: Airflow GCP Secret Manager adapter
Home-page: https://github.com/trustpilot/airflow-gcpsecretmanager-adapter
Author: Trustpilot
Author-email: jge@trustpilot.com
License: UNKNOWN
Project-URL: Bug Tracker, https://github.com/trustpilot/airflow-gcpsecretmanager-adapter/issues
Platform: UNKNOWN
Classifier: Programming Language :: Python :: 3
Classifier: License :: OSI Approved :: MIT License
Classifier: Operating System :: OS Independent
Requires-Python: >=3.6
License-File: LICENSE
Requires-Dist: apache-airflow-providers-google
